mpxapi/__init__.py
mpxapi/api_base.py
mpxapi/exceptions.py
mpxapi/http.py
mpxapi/account/__init__.py
mpxapi/account/media_request.py
mpxapi/adapter/__init__.py
mpxapi/adapter/checksum.py
mpxapi/commerce_configuration/__init__.py
mpxapi/commerce_configuration/rule_set.py
mpxapi/entertainment/__init__.py
mpxapi/entertainment/credit.py
mpxapi/entertainment/person.py
mpxapi/entertainment/program.py
mpxapi/entertainment/program_availability.py
mpxapi/entertainment/tag.py
mpxapi/entertainment/tvseason.py
mpxapi/entitlement/__init__.py
mpxapi/entitlement/entitlements.py
mpxapi/entitlement/rights.py
mpxapi/feeds/__init__.py
mpxapi/feeds/feed_config.py
mpxapi/file_management/__init__.py
mpxapi/file_management/file_management.py
mpxapi/key/__init__.py
mpxapi/key/key.py
mpxapi/media/__init__.py
mpxapi/media/media.py
mpxapi/media/media_file.py
mpxapi/media/provider.py
mpxapi/product/__init__.py
mpxapi/product/pricing_template.py
mpxapi/product/product.py
mpxapi/product/tag.py
mpxapi/promotion/__init__.py
mpxapi/promotion/promotion.py
mpxapi/promotion/promotion_code.py
mpxapi/promotion/promotion_use_count.py
mpxapi/publish/__init__.py
mpxapi/publish/publish_profile.py
mpxapi/storefront/__init__.py
mpxapi/storefront/checkout.py
mpxapi/storefront/ledger_entry.py
mpxapi/storefront/order.py
mpxapi/storefront/order_summary.py
mpxapi/storefront/shipment.py
mpxapi/user/__init__.py
mpxapi/user/user.py
mpxapi/user_profile/__init__.py
mpxapi/user_profile/user_list.py
mpxapi/user_profile/user_list_item.py
mpxapi/user_profile/user_profile.py
mpxapi/workflow/__init__.py
mpxapi/workflow/profile_result.py
mpx_api-0.1.18.dist-info/LICENSE.txt
mpx_api-0.1.18.dist-info/METADATA
mpx_api-0.1.18.dist-info/WHEEL
mpx_api-0.1.18.dist-info/top_level.txt
mpx_api-0.1.18.dist-info/RECORD
