Metadata-Version: 2.1
Name: mpx-api
Version: 0.1.18
Summary: A simple library to interact with Comcast MPX platform
Home-page: http://github.com/blockbuster/mpxapi
Author: Feisal Adur / Blockbuster
Author-email: fea@tdc.dk
License: MIT
Platform: UNKNOWN
License-File: LICENSE.txt
Requires-Dist: requests
